django_pygmentify-0.3.7.dist-info/METADATA
django_pygmentify-0.3.7.dist-info/RECORD
django_pygmentify-0.3.7.dist-info/WHEEL
django_pygmentify-0.3.7.dist-info/top_level.txt
pygmentify/__init__.py
pygmentify/settings.py
pygmentify/static/pygmentify/.DS_Store
pygmentify/static/pygmentify/css/algol.css
pygmentify/static/pygmentify/css/algol.min.css
pygmentify/static/pygmentify/css/algol_nu.css
pygmentify/static/pygmentify/css/algol_nu.min.css
pygmentify/static/pygmentify/css/arduino.css
pygmentify/static/pygmentify/css/arduino.min.css
pygmentify/static/pygmentify/css/autumn.css
pygmentify/static/pygmentify/css/autumn.min.css
pygmentify/static/pygmentify/css/borland.css
pygmentify/static/pygmentify/css/borland.min.css
pygmentify/static/pygmentify/css/bw.css
pygmentify/static/pygmentify/css/bw.min.css
pygmentify/static/pygmentify/css/colorful.css
pygmentify/static/pygmentify/css/colorful.min.css
pygmentify/static/pygmentify/css/default.css
pygmentify/static/pygmentify/css/default.min.css
pygmentify/static/pygmentify/css/emacs.css
pygmentify/static/pygmentify/css/emacs.min.css
pygmentify/static/pygmentify/css/friendly.css
pygmentify/static/pygmentify/css/friendly.min.css
pygmentify/static/pygmentify/css/fruity.css
pygmentify/static/pygmentify/css/fruity.min.css
pygmentify/static/pygmentify/css/igor.css
pygmentify/static/pygmentify/css/igor.min.css
pygmentify/static/pygmentify/css/lovelace.css
pygmentify/static/pygmentify/css/lovelace.min.css
pygmentify/static/pygmentify/css/manni.css
pygmentify/static/pygmentify/css/manni.min.css
pygmentify/static/pygmentify/css/monokai.css
pygmentify/static/pygmentify/css/monokai.min.css
pygmentify/static/pygmentify/css/murphy.css
pygmentify/static/pygmentify/css/murphy.min.css
pygmentify/static/pygmentify/css/native.css
pygmentify/static/pygmentify/css/native.min.css
pygmentify/static/pygmentify/css/paraiso-dark.css
pygmentify/static/pygmentify/css/paraiso-dark.min.css
pygmentify/static/pygmentify/css/paraiso-light.css
pygmentify/static/pygmentify/css/paraiso-light.min.css
pygmentify/static/pygmentify/css/pastie.css
pygmentify/static/pygmentify/css/pastie.min.css
